chainercb/__init__.py
chainercb/bandify.py
chainercb/loss.py
chainercb/policy.py
chainercb/policies/__init__.py
chainercb/policies/adf.py
chainercb/policies/adf_ucb.py
chainercb/policies/epsilon_greedy.py
chainercb/policies/exploit.py
chainercb/policies/explore.py
chainercb/policies/linear.py
chainercb/policies/linear_thompson.py
chainercb/policies/linear_ucb.py
chainercb/policies/softmax.py
chainercb/util/__init__.py
chainercb/util/ridge.py
chainercb/util/select_items.py
test/__init__.py
test/policy.py
test/test_policy.py
test/policies/__init__.py
test/policies/test_adf_ucb.py
test/policies/test_epsilon_greedy.py
test/policies/test_exploit.py
test/policies/test_explore.py
test/policies/test_linear_thompson.py
test/policies/test_linear_ucb.py
test/policies/test_softmax.py
test/util/__init__.py
test/util/test_ridge.py
chainercb-0.2.3.dist-info/LICENSE
chainercb-0.2.3.dist-info/METADATA
chainercb-0.2.3.dist-info/WHEEL
chainercb-0.2.3.dist-info/top_level.txt
chainercb-0.2.3.dist-info/RECORD
