Metadata-Version: 2.1
Name: chainercb
Version: 0.2.3
Summary: Neural Contextual Bandits using Chainer
Home-page: https://github.com/rjagerman/chainercb
Author: Rolf Jagerman
Author-email: rjagerman@gmail.com
License: MIT
Download-URL: https://github.com/rjagerman/chainercb/archive/v0.2.3.tar.gz
Platform: UNKNOWN
Requires-Dist: numpy (>=1.13.0)
Requires-Dist: chainer (>=3.0.0)
